odoo9_addon_sale_reporting_weight-9.0.1.0.0-py2.7-nspkg.pth
odoo9_addon_sale_reporting_weight-9.0.1.0.0.dist-info/top_level.txt
odoo9_addon_sale_reporting_weight-9.0.1.0.0.dist-info/WHEEL
odoo9_addon_sale_reporting_weight-9.0.1.0.0.dist-info/RECORD
odoo9_addon_sale_reporting_weight-9.0.1.0.0.dist-info/metadata.json
odoo9_addon_sale_reporting_weight-9.0.1.0.0.dist-info/DESCRIPTION.rst
odoo9_addon_sale_reporting_weight-9.0.1.0.0.dist-info/METADATA
odoo9_addon_sale_reporting_weight-9.0.1.0.0.dist-info/namespace_packages.txt
odoo_addons/sale_reporting_weight/__openerp__.py
odoo_addons/sale_reporting_weight/__init__.py
odoo_addons/sale_reporting_weight/README.rst
odoo_addons/sale_reporting_weight/i18n/es.po
odoo_addons/sale_reporting_weight/reports/__init__.py
odoo_addons/sale_reporting_weight/reports/sale_report.py
